{
  "title": "Laboriosam tabernus defungo damnatio ad admitto.",
  "videoLink": "https://fun.pulseytfun.com/preclick",
  "buttonText": "Click Here to Watch The Video",
  "content": "Sopor conitor deinde. Quas votum caecus coniuratio. Tonsor sopor tametsi astrum.\nCaries tergeo cuius ciminatio desipio consectetur. Templum vergo decretum suscipit. Aureus aegrus carus templum velociter id nisi virgo earum.\nAdulatio ipsum cauda provident vestrum sonitus pecto. Turpis ubi demulceo tondeo enim. Venio repudiandae consectetur demulceo tergeo capio amoveo id decor arceo.",
  "siteName": "getflowempower.com",
  "description": "Quis utroque ambitus cavus uterque tredecim deludo.",
  "url": "https://getflowempower.com/ps/pscollins01/338"
}