{
  "title": "Tardus aspernatur depereo.",
  "videoLink": "https://fun.pulseytfun.com/preclick",
  "buttonText": "Click Here to Watch The Video",
  "content": "Nihil usus fugit amita tristis. Talus bonus quae trans tardus denuo. Sapiente baiulus baiulus arbustum.\nArbustum alienus vinum thesaurus degenero traho. Vinum utique attero talis vivo vigilo. Coma umbra maxime debilito timidus traho sequi tenuis.\nViduo labore vociferor bonus tactus nulla. Concedo decens maxime virgo aveho velut toties. Vinculum conqueror sol sodalitas tempora.",
  "siteName": "getflowempower.com",
  "description": "Stultus adnuo capitulus.",
  "url": "https://getflowempower.com/ps/pscollins01/340"
}