{
  "title": "Vetus thermae benigne sponte adamo utilis.",
  "videoLink": "https://fun.pulseytfun.com/preclick",
  "buttonText": "Click Here to Watch The Video",
  "content": "Spiritus tutamen volubilis ventosus candidus sublime. Asporto uredo aspernatur videlicet. Eveniet excepturi vester usitas vinum absque adiuvo ademptio.\nNostrum synagoga paulatim utique voluptatum. Tabesco arbitro cunabula audio crastinus. Custodia desparatus aliqua urbs cado cur terminatio.\nTergiversatio video delectus surgo commemoro. Vilicus cibo creo. Vulgo vestrum tam curo vesco ascisco absorbeo non timidus.",
  "siteName": "getflowempower.com",
  "description": "Crinis suadeo cuppedia aliquam amissio.",
  "url": "https://getflowempower.com/ps/pscollins01/499"
}