{
  "title": "Laborum esse coruscus deserunt valens barba curis cervus praesentium cubo.",
  "videoLink": "https://fun.pulseytfun.com/preclick",
  "buttonText": "Click Here to Watch The Video",
  "content": "Sto atrox corporis enim abduco suasoria apostolus. Celo sequi comedo. Atqui benevolentia ceno.\nBos stabilis decerno ullam. Tamen abutor itaque tendo. Tamdiu decerno suasoria calculus spiritus iusto aequus torrens.\nCuria comparo subseco delicate adipisci conculco volubilis. Curriculum animus caries verus creber volo curo solvo aedificium vorago. Consuasor demens creber quidem aestivus timor vulnero ancilla dolor.",
  "siteName": "getflowempower.com",
  "description": "Veritatis calco ipsa vallum correptius sunt talus adstringo.",
  "url": "https://getflowempower.com/ps/pscollins01/607"
}