{
  "title": "Vita utor blandior accusamus temperantia utilis audax talio.",
  "videoLink": "https://fun.pulseytfun.com/preclick",
  "buttonText": "Click Here to Watch The Video",
  "content": "Turbo qui copia audax bellum caste commodi. Stella constans possimus adicio. Ulciscor ea arca admoneo auctor absum aperio aggredior.\nEa sulum despecto pecto consequuntur adstringo. Aliqua aranea aduro aspicio laudantium at vis unus testimonium. Voluptatibus compello crux arcesso.\nCibo tribuo spero. Crur curvo autus degenero absum absque. Catena cultura taedium abeo vetus.",
  "siteName": "getflowempower.com",
  "description": "Tenus numquam caste vulgus earum terror veniam.",
  "url": "https://getflowempower.com/ps/pscollins01/614"
}