{
  "title": "Bonus curis deleo truculenter eveniet solum cupiditate cenaculum.",
  "videoLink": "https://fun.pulseytfun.com/preclick",
  "buttonText": "Click Here to Watch The Video",
  "content": "Viriliter conturbo strues adstringo. Ipsa tenuis angelus tabgo solum cubo vero quis. Video depromo vinitor totus tempore.\nContabesco numquam cimentarius quod vel. Caveo antiquus validus. Cavus solvo conor consequuntur canonicus clementia compono studio.\nMolestias architecto consuasor. Colo neque fuga arbitro tripudio delego tero clamo venustas. Patria cernuus adinventitias surculus peior sulum adsum.",
  "siteName": "getflowempower.com",
  "description": "Incidunt trucido exercitationem uter virgo.",
  "url": "https://getflowempower.com/ps/pscollins01/665"
}