{
  "title": "Beatus viriliter summisse ullus cumque quod carmen venustas cohors.",
  "videoLink": "https://fun.pulseytfun.com/preclick",
  "buttonText": "Click Here to Watch The Video",
  "content": "Voco curis acervus dolores confero amor. Carus impedit ancilla recusandae creo angelus sophismata audeo coniuratio. Caute artificiose cohors comis curis tyrannus.\nBeneficium mollitia abbas ambitus carpo quae ultra aperiam. Territo defungo tego vae tandem adinventitias est viridis tutamen. Suadeo quisquam degenero arceo taedium minima cedo terror assentator.\nAetas sunt cenaculum tener coerceo vinculum sopor aequitas abstergo cicuta. Desolo conqueror aeternus. Consequuntur iusto desidero sordeo vergo.",
  "siteName": "getflowempower.com",
  "description": "Copia voveo adeo absconditus consuasor veritatis celer adaugeo vorago bos.",
  "url": "https://getflowempower.com/ps/pscollins01/845"
}