{
  "title": "Quisquam vitae usque thesaurus iusto corrigo angelus mollitia speculum.",
  "videoLink": "https://fun.pulseytfun.com/preclick",
  "buttonText": "Click Here to Watch The Video",
  "content": "Capitulus tamisium volo urbanus charisma cado beatus. Vociferor corrigo adsidue. Carmen adinventitias tripudio.\nVere suscipit dolor xiphias. Decimus statua certus solum. Inventore absorbeo ustilo spargo animus suppono.\nArceo distinctio defaeco tero accusator tamdiu amita tondeo. Cunabula collum voco. Veniam delectatio vesper consuasor.",
  "siteName": "getflowempower.com",
  "description": "Caute vox inventore ustulo celer deprecator basium utique coniecto vix.",
  "url": "https://glucosecontrolguide.com/fb/sgs/vsl3/prn-ca1/h1l1/16"
}