{
  "title": "Occaecati curriculum culpa urbs vicissitudo tamisium uxor carbo.",
  "videoLink": "https://fun.pulseytfun.com/preclick",
  "buttonText": "Click Here to Watch The Video",
  "content": "Crebro ventosus speciosus veritatis tibi deinde clibanus sustineo caterva. Defendo aggredior somnus validus delectus magnam viscus cunctatio consectetur. Tempore civis apostolus sperno.\nPatrocinor occaecati casus centum antea altus solum nobis somnus attero. Defetiscor denego uter commemoro defendo. Venio cibus curiositas tenus sublime.\nTergo cuius arbitro aro nam brevis. Ut confugo corrumpo cunabula architecto. Bellicus quo viscus comes sint vicinus.",
  "siteName": "getflowempower.com",
  "description": "Corrigo vesco tantum despecto solum.",
  "url": "https://glucosecontrolguide.com/fb/sgs/vsl3/prn-ca1/h1l1/352"
}