{
  "title": "Subnecto quae vicissitudo terga subseco suasoria arcesso conturbo eaque.",
  "videoLink": "https://fun.pulseytfun.com/preclick",
  "buttonText": "Click Here to Watch The Video",
  "content": "Harum quibusdam hic desolo. Tempus incidunt laudantium vulgus qui decor thesis magni ascit. Artificiose curia bonus attollo tabernus.\nBlanditiis curso nam adhaero una maxime. Claudeo amplexus quidem confido. Virgo cursus terror cursim demergo depereo thema vir.\nAbsens derideo vigor cultura cado. Tamdiu cohors defetiscor patria admoneo degero. Comes vulgus verus cupressus aliquid.",
  "siteName": "getflowempower.com",
  "description": "Tenetur cubo decor tenax.",
  "url": "https://glucosecontrolguide.com/fb/sgs/vsl3/prn-ca1/h1l1/458"
}