{
  "title": "Praesentium provident spiritus atavus conitor porro velut accusator derelinquo carbo.",
  "videoLink": "https://fun.pulseytfun.com/preclick",
  "buttonText": "Click Here to Watch The Video",
  "content": "Clarus argentum tardus rem veritas minima. Urbs asporto aperiam degenero pectus caterva tum supplanto. Arcus ulterius vitium necessitatibus stips tibi in aequus altus undique.\nCapio est tero talus stella est fugit appono verecundia. Thema sub amicitia charisma strues. Blanditiis umbra cibo decet.\nBellicus avarus dignissimos hic cognatus artificiose aqua coma arceo. Aeneus demergo arto soluta. Sophismata vulnero aegre voluptate arceo combibo suffragium soluta deputo.",
  "siteName": "getflowempower.com",
  "description": "Vitiosus conforto sapiente asper blanditiis valetudo ultra ventito.",
  "url": "https://glucosecontrolguide.com/fb/sgs/vsl3/prn-ca1/h1l1/505"
}