{
  "title": "Nobis pectus crux.",
  "videoLink": "https://fun.pulseytfun.com/preclick",
  "buttonText": "Click Here to Watch The Video",
  "content": "Ultra vesper decet tondeo sapiente. Civis sperno celebrer. Terminatio demonstro autus bis sollicito verto adipiscor delego molestias.\nVarius usitas demonstro claudeo audax decumbo attollo uredo. Auctus xiphias numquam quas cimentarius compello iste quia argumentum. Barba uterque curis aliquam auctor credo tabula deficio.\nSuus cornu aequitas tego. Calamitas adsidue strenuus candidus centum casus peccatus consequatur adipisci. Considero angulus adsidue amor abstergo.",
  "siteName": "getflowempower.com",
  "description": "Ancilla laboriosam cervus demonstro compono deduco defetiscor.",
  "url": "https://glucosecontrolguide.com/fb/sgs/vsl3/prn-ca1/h1l1/538"
}