{
  "title": "Comitatus tollo comedo vesper voluptatum.",
  "videoLink": "https://fun.pulseytfun.com/preclick",
  "buttonText": "Click Here to Watch The Video",
  "content": "Cito sit sponte torrens tabesco tergeo nisi ante talis quas. Coniecto admitto tolero inventore credo casso coniuratio depulso deduco tracto. Aperio valde thalassinus viscus adversus casus quos censura et vulgus.\nDebilito vitium debeo verecundia cado vito. Ceno demergo crux ventus vix. Adulescens degusto nobis cohors inventore tot nesciunt.\nAvarus surgo unus non apto id sub. Deputo conqueror vesper animus trepide angustus. Clamo utilis possimus acer cursim cognatus.",
  "siteName": "getflowempower.com",
  "description": "Depromo minus corporis derelinquo bibo angustus tabula crebro iusto.",
  "url": "https://glucosecontrolguide.com/fb/sgs/vsl3/prn-ca1/h1l1/54"
}