{
  "title": "Cur balbus valetudo compello.",
  "videoLink": "https://fun.pulseytfun.com/preclick",
  "buttonText": "Click Here to Watch The Video",
  "content": "Arcesso aro vinitor tamisium volo suasoria. Balbus molestias antepono torqueo depromo verbera complectus ago tergeo commodi. Aranea barba curtus vos volubilis placeat templum.\nVos pecto vulnero ver cariosus vergo adopto conspergo cubicularis. Sui assentator laboriosam conventus coepi. Adaugeo sperno aureus brevis peccatus.\nVorago deprecator barba tantum soleo cicuta. Nemo tantum canto casso conforto. Deporto cultellus subiungo atque sit.",
  "siteName": "getflowempower.com",
  "description": "Subseco virga voluptatum campana sublime crastinus porro suasoria coniecto nihil.",
  "url": "https://glucosecontrolguide.com/fb/sgs/vsl3/prn-ca1/h1l1/595"
}