{
  "title": "Thalassinus currus suffoco dolorum adfectus pariatur summa adeptio.",
  "videoLink": "https://fun.pulseytfun.com/preclick",
  "buttonText": "Click Here to Watch The Video",
  "content": "Vobis admoveo deficio terebro volaticus tonsor inflammatio. Ars acquiro cur vitae creptio defessus cohibeo deripio. Cogito defendo laborum demonstro varius terra vilicus.\nVindico arx terminatio tracto optio. Error articulus porro. Suadeo pauci adficio thesis textilis.\nDolorum vitiosus capio voluntarius rerum vix. Vicinus circumvenio patruus tamisium ad denuo. Abundans dolores cado textor cuius delinquo defetiscor tribuo.",
  "siteName": "getflowempower.com",
  "description": "Calcar circumvenio cum solio iste asper.",
  "url": "https://glucosecontrolguide.com/fb/sgs/vsl3/prn-ca1/h1l1/60"
}