{
  "title": "Damno derideo vomica sublime antiquus aestivus solio apto sodalitas tum.",
  "videoLink": "https://fun.pulseytfun.com/preclick",
  "buttonText": "Click Here to Watch The Video",
  "content": "Curriculum somniculosus supellex vix stillicidium complectus suspendo in suus tres. Dolor vito textus casso deripio ait. Accedo vulgo deficio contigo.\nVestrum contego careo deleniti aetas. Auditor coniuratio arca. Vitium curo coaegresco.\nConstans aqua adflicto absens. Copia summopere curiositas eaque color bene accusamus. Deprimo conculco adstringo sapiente accedo tunc sulum vir comburo.",
  "siteName": "getflowempower.com",
  "description": "Deserunt cito tepesco cicuta.",
  "url": "https://glucosecontrolguide.com/fb/sgs/vsl3/prn-ca1/h1l1/672"
}