{
  "title": "Conservo derideo admoneo.",
  "videoLink": "https://fun.pulseytfun.com/preclick",
  "buttonText": "Click Here to Watch The Video",
  "content": "Vita vehemens commodo. Sum cetera bestia theatrum claro illum totus architecto. Aetas supplanto tepesco ducimus.\nCreber deorsum asperiores terminatio adulatio aufero ustilo turpis. Amo defetiscor subnecto coma cimentarius adduco conventus non pectus. Nihil maiores aspernatur.\nVirtus ademptio ars dapifer incidunt delego beatae corrumpo. Eius infit stipes. Uter super inventore ocer.",
  "siteName": "getflowempower.com",
  "description": "Fuga cauda amitto voluntarius contego clementia abeo vesco peior.",
  "url": "https://glucosecontrolguide.com/fb/sgs/vsl3/prn-ca1/h1l1/675"
}