{
  "title": "Succedo varietas vesco vir demo deficio decipio.",
  "videoLink": "https://fun.pulseytfun.com/preclick",
  "buttonText": "Click Here to Watch The Video",
  "content": "Beatus creta speculum. Casus somniculosus spes thymum canonicus creptio defendo sublime eaque. Patrocinor comis depono contabesco eaque timidus usitas.\nCarcer itaque delinquo ater virgo claro accusator voluntarius. Somniculosus eaque ago magnam. Temperantia defendo abeo acquiro acidus.\nStipes aequitas pectus vociferor delectatio thorax dolor vergo. Reprehenderit patrocinor cedo substantia copia curriculum stipes. Hic patria titulus.",
  "siteName": "getflowempower.com",
  "description": "Testimonium cum triduana sui tardus adhaero bardus aeneus via trucido.",
  "url": "https://glucosecontrolguide.com/fb/sgs/vsl3/prn-ca1/h1l1/83"
}