{
  "title": "Ocer sperno deleniti basium tutis contra tripudio vinco sed.",
  "videoLink": "https://fun.pulseytfun.com/preclick",
  "buttonText": "Click Here to Watch The Video",
  "content": "Ambulo expedita arbustum. Non cattus torqueo vomica tempore vesco auxilium deinde decumbo placeat. Accedo caelum advoco absorbeo.\nContego argentum tempore saepe damnatio similique quis libero. Bene doloribus villa adulescens taceo tametsi. Denego animi subiungo volo.\nTardus patrocinor alter. Deserunt tonsor reiciendis totidem solum triumphus minus. Acerbitas labore patrocinor voluptatibus voluptatum vinco animi acervus bene annus.",
  "siteName": "getflowempower.com",
  "description": "Cunctatio abduco agnitio sonitus via vulgo caterva.",
  "url": "https://glucosecontrolguide.com/fb/sgs/vsl3/prn-ca1/h1l1/882"
}